{"running": false, "frame": 295, "total_frames": 295, "fps": 8.3, "duration": 35, "session_id": "20260420_023629", "video_name": "AI Enhancer-Ultra HD-WhatsApp Video 2026-04-17 at 5.40.19 PM.mp4", "resolution": "478x850", "threshold": 0.65, "persons": [{"id": 1, "score": 0.7912, "confidence": 0.5823, "frames_analyzed": 83, "is_deepfake": true, "is_uncertain": false}, {"id": 4, "score": 0.6016, "confidence": 0.2032, "frames_analyzed": 9, "is_deepfake": false, "is_uncertain": true}, {"id": 6, "score": 0.5, "confidence": 0.0, "frames_analyzed": 1, "is_deepfake": false, "is_uncertain": true}, {"id": 13, "score": 0.5, "confidence": 0.0, "frames_analyzed": 1, "is_deepfake": false, "is_uncertain": true}], "alerts": [], "videos_done": 1, "status": "done"}